LICENSE.txt
README.md
setup.py
rocket/__init__.py
rocket/rocket.py
rocket_pkg_mrkhaldi.egg-info/PKG-INFO
rocket_pkg_mrkhaldi.egg-info/SOURCES.txt
rocket_pkg_mrkhaldi.egg-info/dependency_links.txt
rocket_pkg_mrkhaldi.egg-info/requires.txt
rocket_pkg_mrkhaldi.egg-info/top_level.txt