Metadata-Version: 2.1
Name: rocket-pkg-mrkhaldi
Version: 1.0.0
Summary: An awesome package that does something
Home-page: http://pypi.python.org/pypi/rocket/
Author: KHALDI Mohamed Rafik
Author-email: mr.khaldi@esi-sba.dz
License: LICENSE.txt
License-File: LICENSE.txt
Requires-Dist: rocket
